skyfetch/__init__.py
skyfetch/temp.py
skyfetch-0.0.1.dist-info/METADATA
skyfetch-0.0.1.dist-info/WHEEL
skyfetch-0.0.1.dist-info/RECORD
